qywx_bot/__init__.py
qywx_bot/bot.py
qywx_bot/check.py
qywx_bot-1.4.dist-info/LICENSE
qywx_bot-1.4.dist-info/METADATA
qywx_bot-1.4.dist-info/WHEEL
qywx_bot-1.4.dist-info/top_level.txt
qywx_bot-1.4.dist-info/RECORD
