Metadata-Version: 2.1
Name: qywx-bot
Version: 1.4
Summary: python sdk for work wechat robots
Home-page: https://github.com/sun2ot/qywx-bot
Author: sun2ot
Author-email: sun2ot@qq.com
Classifier: Programming Language :: Python :: 3
Classifier: License :: OSI Approved :: MIT License
Classifier: Operating System :: OS Independent
Requires-Python: >=3
License-File: LICENSE
Requires-Dist: requests
